LICENSE
README.md
setup.cfg
setup.py
DataExploration/__init__.py
DataExploration/bivariate.py
DataExploration/univariate.py
dexploize.egg-info/PKG-INFO
dexploize.egg-info/SOURCES.txt
dexploize.egg-info/dependency_links.txt
dexploize.egg-info/entry_points.txt
dexploize.egg-info/requires.txt
dexploize.egg-info/top_level.txt
tests/__init__.py