Metadata-Version: 2.1
Name: dexploize
Version: 0.1.1
Summary: dexploize (data exploration) python library use for applying different foundational techniques such as univariate and bivariate analysis.
Home-page: https://github.com/iyaniyan11/dexploize.git
Author: Christian Garcia
Author-email: iyaniyan3112003@gmail.com
License: MIT
Classifier: Programming Language :: Python :: 3
Classifier: License :: OSI Approved :: MIT License
Classifier: Operating System :: OS Independent
Classifier: Topic :: Software Development :: Libraries :: Python Modules
License-File: LICENSE
Requires-Dist: matplotlib>=3.4.3
Requires-Dist: numpy>=1.21.0
Requires-Dist: pandas>=1.3.3
